scroll_renderer/__init__.py
scroll_renderer/finalize_mesh.py
scroll_renderer/large_mesh_to_surface.py
scroll_renderer/mesh_to_surface.py
scroll_renderer/slim_uv.py
scroll_renderer/rendering_utils/__init__.py
scroll_renderer/rendering_utils/interpolate_image_3d.py
scroll_renderer-0.0.2.dist-info/METADATA
scroll_renderer-0.0.2.dist-info/WHEEL
scroll_renderer-0.0.2.dist-info/entry_points.txt
scroll_renderer-0.0.2.dist-info/top_level.txt
scroll_renderer-0.0.2.dist-info/RECORD
