Metadata-Version: 2.1
Name: scroll_renderer
Version: 0.0.2
Summary: A package for flattening and rendering 3D meshes of segments of the Herculaneum Papyri.
Home-page: https://github.com/ScrollPrize/villa
Author: Vesuvius Challenge Team
Author-email: team@scrollprize.org
Classifier: Programming Language :: Python :: 3
Classifier: Programming Language :: Python :: 3.11
Classifier: License :: OSI Approved :: MIT License
Classifier: Operating System :: OS Independent
Classifier: Intended Audience :: Developers
Classifier: Intended Audience :: Science/Research
Classifier: Topic :: Software Development :: Libraries
Classifier: Topic :: Scientific/Engineering
Requires-Dist: numpy
Requires-Dist: tqdm
Requires-Dist: Pillow
Requires-Dist: opencv-python
Requires-Dist: scipy
Requires-Dist: tifffile
Requires-Dist: dask
Requires-Dist: dask-image
Requires-Dist: zarr
Requires-Dist: einops
Requires-Dist: torch
Requires-Dist: pytorch-lightning
Requires-Dist: open3d
Requires-Dist: libigl
Requires-Dist: vesuvius
Requires-Dist: psutil
